{
  "parent": "minecraft:recipes/root",
  "criteria": {
    "has_chainmail_gloves": {
      "conditions": {
        "items": [
          {
            "items": [
              "aether:chainmail_gloves"
            ]
          }
        ]
      },
      "trigger": "minecraft:inventory_changed"
    },
    "has_iron_gloves": {
      "conditions": {
        "items": [
          {
            "items": [
              "aether:iron_gloves"
            ]
          }
        ]
      },
      "trigger": "minecraft:inventory_changed"
    },
    "has_iron_pendant": {
      "conditions": {
        "items": [
          {
            "items": [
              "aether:iron_pendant"
            ]
          }
        ]
      },
      "trigger": "minecraft:inventory_changed"
    },
    "has_iron_ring": {
      "conditions": {
        "items": [
          {
            "items": [
              "aether:iron_ring"
            ]
          }
        ]
      },
      "trigger": "minecraft:inventory_changed"
    },
    "has_the_recipe": {
      "conditions": {
        "recipe": "aether:aether_iron_nugget_from_blasting"
      },
      "trigger": "minecraft:recipe_unlocked"
    }
  },
  "requirements": [
    [
      "has_iron_gloves",
      "has_iron_pendant",
      "has_iron_ring",
      "has_chainmail_gloves",
      "has_the_recipe"
    ]
  ],
  "rewards": {
    "recipes": [
      "aether:aether_iron_nugget_from_blasting"
    ]
  },
  "sends_telemetry_event": false
}