{
  "parent": "minecraft:recipes/root",
  "criteria": {
    "has_skyroot_sword": {
      "conditions": {
        "items": [
          {
            "items": [
              "aether:skyroot_sword"
            ]
          }
        ]
      },
      "trigger": "minecraft:inventory_changed"
    },
    "has_the_recipe": {
      "conditions": {
        "recipe": "aether:skyroot_sword_repairing"
      },
      "trigger": "minecraft:recipe_unlocked"
    }
  },
  "requirements": [
    [
      "has_the_recipe",
      "has_skyroot_sword"
    ]
  ],
  "rewards": {
    "recipes": [
      "aether:skyroot_sword_repairing"
    ]
  },
  "sends_telemetry_event": false
}